.travis.yml
AUTHORS
COMPLETION.md
ChangeLog
LICENSE
README.md
VERSION
requirements.txt
setup.cfg
setup.py
test-requirements.txt
vsd-creds.example
open_vsdcli/__init__.py
open_vsdcli/vsd_client.py
open_vsdcli/vsd_common.py
open_vsdcli/vsd_dhcp.py
open_vsdcli/vsd_domain.py
open_vsdcli/vsd_enterprise.py
open_vsdcli/vsd_gateway.py
open_vsdcli/vsd_license.py
open_vsdcli/vsd_metadata.py
open_vsdcli/vsd_policy.py
open_vsdcli/vsd_route.py
open_vsdcli/vsd_subnet.py
open_vsdcli/vsd_user.py
open_vsdcli/vsd_vm.py
open_vsdcli/vsd_vport.py
open_vsdcli/vsd_vsp.py
open_vsdcli/vsdcli.py
open_vsdcli.egg-info/PKG-INFO
open_vsdcli.egg-info/SOURCES.txt
open_vsdcli.egg-info/dependency_links.txt
open_vsdcli.egg-info/entry_points.txt
open_vsdcli.egg-info/not-zip-safe
open_vsdcli.egg-info/pbr.json
open_vsdcli.egg-info/requires.txt
open_vsdcli.egg-info/top_level.txt
tests/common.bash
tests/creds-mock
tests/helpers.bash
tests/run_tests.sh
tests/test.bats
tests/test_dhcp.bats
tests/test_domain.bats
tests/test_enterprise.bats
tests/test_gateway.bats
tests/test_license.bats
tests/test_metadata.bats
tests/test_policy.bats
tests/test_redundancygroups.bats
tests/test_route.bats
tests/test_subnet.bats
tests/test_user.bats
tests/test_vm.bats
tests/test_vport.bats
tests/test_vsdcli.bats
tests/vsd_mock.py