Metadata-Version: 1.0
Name: open-vsdcli
Version: 0.4.0
Summary: CLI for Nuage VSD
Home-page: http://www.github.com/maxiterr/open-vsdcli
Author: Maxime Terras
Author-email: maxime.terras@numergy.com
License: MIT
Platform: UNKNOWN
